nlp_uncertainty_zoo/__init__.py
nlp_uncertainty_zoo/config.py
nlp_uncertainty_zoo/defaults.py
nlp_uncertainty_zoo/models/__init__.py
nlp_uncertainty_zoo/models/bayesian_lstm.py
nlp_uncertainty_zoo/models/bert.py
nlp_uncertainty_zoo/models/ddu_transformer.py
nlp_uncertainty_zoo/models/dpp_transformer.py
nlp_uncertainty_zoo/models/lstm.py
nlp_uncertainty_zoo/models/lstm_ensemble.py
nlp_uncertainty_zoo/models/model.py
nlp_uncertainty_zoo/models/sngp_transformer.py
nlp_uncertainty_zoo/models/spectral.py
nlp_uncertainty_zoo/models/st_tau_lstm.py
nlp_uncertainty_zoo/models/transformer.py
nlp_uncertainty_zoo/models/variational_lstm.py
nlp_uncertainty_zoo/models/variational_transformer.py
nlp_uncertainty_zoo/tests/__init__.py
nlp_uncertainty_zoo/tests/test_module_functions.py
nlp_uncertainty_zoo/utils/__init__.py
nlp_uncertainty_zoo/utils/calibration_eval.py
nlp_uncertainty_zoo/utils/custom_types.py
nlp_uncertainty_zoo/utils/data.py
nlp_uncertainty_zoo/utils/metrics.py
nlp_uncertainty_zoo/utils/samplers.py
nlp_uncertainty_zoo/utils/task_eval.py
nlp_uncertainty_zoo/utils/uncertainty_eval.py
nlp_uncertainty_zoo-1.0.3.dist-info/METADATA
nlp_uncertainty_zoo-1.0.3.dist-info/WHEEL
nlp_uncertainty_zoo-1.0.3.dist-info/top_level.txt
nlp_uncertainty_zoo-1.0.3.dist-info/RECORD
