Metadata-Version: 2.1
Name: nlp-uncertainty-zoo
Version: 1.0.3
Summary: PyTorch Implementation of Models used for Uncertainty Estimation in Natural Language Processing.
Home-page: https://github.com/Kaleidophon/nlp-uncertainty-zoo
Author: Dennis Ulmer
License: GPL
Keywords: machine learning,deep learning,nlp,uncertainty,uncertainty estimationpytorch
Platform: UNKNOWN
Classifier: Intended Audience :: Science/Research
Classifier: Topic :: Scientific/Engineering :: Artificial Intelligence
Classifier: Programming Language :: Python :: 3
Classifier: Operating System :: OS Independent
Requires-Python: >=3.5.3
Requires-Dist: torch (>=1.9.0)
Requires-Dist: numpy (>=1.19.5)
Requires-Dist: wandb (>=0.12.5)
Requires-Dist: scikit-learn (>=0.24.1)
Requires-Dist: transformers (>=4.5.1)
Requires-Dist: einops (>=0.3.0)
Requires-Dist: datasets (>=1.6.2)
Requires-Dist: tqdm (>=4.49.0)
Requires-Dist: blitz-bayesian-pytorch (>=0.2.7)
Requires-Dist: gpytorch (>=1.5.0)
Requires-Dist: scipy (>=1.5.4)
Requires-Dist: dill (>=0.3.3)
Requires-Dist: joblib (>=1.0.1)
Requires-Dist: alpaca-ml (>=0.8.2)
Requires-Dist: frozendict (==2.3.4)
Requires-Dist: protobuf (==3.20.0)
